<?xml version="1.0" encoding="utf-8" ?>
<dwsync>
<file name="1-1505171119.jpg" server="qxu1192680294.my3w.com//htdocs/" local="130762656000000000" remote="130762656000000000" Dst="0" />
<file name="1-1505171120.jpg" server="qxu1192680294.my3w.com//htdocs/" local="130762656000000000" remote="130762656000000000" Dst="0" />
<file name="1-1505171124.jpg" server="qxu1192680294.my3w.com//htdocs/" local="130762656000000000" remote="130762656000000000" Dst="0" />
<file name="1-1505171135.jpg" server="qxu1192680294.my3w.com//htdocs/" local="130762656000000000" remote="130762656000000000" Dst="0" />
<file name="1-1505180752.jpg" server="qxu1192680294.my3w.com//htdocs/" local="130763520000000000" remote="130763520000000000" Dst="0" />
<file name="1-1505221028.jpg" server="qxu1192680294.my3w.com//htdocs/" local="130766976000000000" remote="130766976000000000" Dst="0" />
<file name="2-1505310502.jpg" server="qxu1192680294.my3w.com//htdocs/" local="130775365646030132" remote="130775558400000000" Dst="0" />
<file name="2-1506040535.jpg" server="qxu1192680294.my3w.com//htdocs/" local="130778841000000000" remote="130778841000000000" Dst="0" />
<file name="23-1506011056.jpg" server="qxu1192680294.my3w.com//htdocs/" local="130776009600000000" remote="130776009600000000" Dst="0" />
<file name="-1508211245.jpg" server="qxu1192680294.my3w.com//htdocs/" local="130845627363613396" remote="130929318600000000" Dst="0" />
<file name="-1508211250.jpg" server="qxu1192680294.my3w.com//htdocs/" local="130845630426900529" remote="130929318600000000" Dst="0" />
</dwsync>