<?xml version="1.0" encoding="utf-8" ?>
<dwsync>
<file name="v.js" server="121.196.226.94" local="130948383943040185" remote="130948389000000000" Dst="0" />
<file name="analytics.js" server="121.196.226.94" local="130948383952571385" remote="130948389000000000" Dst="0" />
<file name="common.js" server="121.196.226.94" local="130948387421762061" remote="130948389000000000" Dst="0" />
<file name="config.js" server="121.196.226.94" local="130948383956771932" remote="130948389000000000" Dst="0" />
<file name="contains.js" server="121.196.226.94" local="130948383942210080" remote="130948389000000000" Dst="0" />
<file name="hm.js" server="121.196.226.94" local="130948387424802449" remote="130948389000000000" Dst="0" />
<file name="page.js" server="121.196.226.94" local="130948387428302873" remote="130948389000000000" Dst="0" />
<file name="Panel.js" server="121.196.226.94" local="130948383946430626" remote="130948389000000000" Dst="0" />
<file name="bootstrap.min.js" server="121.196.226.94" local="130947188614101181" remote="130946544600000000" Dst="0" />
<file name="jquery.binddata.js" server="121.196.226.94" local="130947188621006464" remote="130946544600000000" Dst="0" />
<file name="jquery-1.8.3.min.js" server="121.196.226.94" local="130947188621636556" remote="130946541000000000" Dst="0" />
<file name="jquery.DB_tabMotionBanner.min.js" server="121.196.226.94" local="130947188623106742" remote="130946541000000000" Dst="0" />
<file name="jquery.serializejson.min.js" server="121.196.226.94" local="130947188623106742" remote="130946544600000000" Dst="0" />
<file name="jquery-1.10.2.js" server="121.196.226.94" local="130947188623176760" remote="130946544600000000" Dst="0" />
<file name="json2.js" server="121.196.226.94" local="130947188624916965" remote="130946544600000000" Dst="0" />
<file name="layer.ext.js" server="121.196.226.94" local="130947188625116991" remote="130946560800000000" Dst="0" />
<file name="layer.js" server="121.196.226.94" local="130947188625547044" remote="130946560800000000" Dst="0" />
<file name="jquery.validate.js" server="121.196.226.94" local="130947188626007112" remote="130946544600000000" Dst="0" />
<file name="localStorage.js" server="121.196.226.94" local="130948383944480378" remote="130948389000000000" Dst="0" />
<file name="area.js" server="121.196.226.94" local="130948383966663194" remote="130948389000000000" Dst="0" />
<file name="localStorage1.js" server="121.196.226.94" local="130947973768513469" remote="130948389000000000" Dst="0" />
</dwsync>